ontologize/__init__.py
ontologize/__main__.py
ontologize/biocyc.py
ontologize/cli.py
ontologize/defaults.py
ontologize/ontology.py
ontologize-0.2.0.dist-info/LICENSE
ontologize-0.2.0.dist-info/METADATA
ontologize-0.2.0.dist-info/WHEEL
ontologize-0.2.0.dist-info/entry_points.txt
ontologize-0.2.0.dist-info/top_level.txt
ontologize-0.2.0.dist-info/RECORD
