Metadata-Version: 2.1
Name: ontologize
Version: 0.2.0
Summary: Build annotated ontologies for BioCyc objects
Author: Mica Yang
License: MIT License
Project-URL: Homepage, https://github.com/Robotato/ontologize
Keywords: biocyc,ecocyc,metacyc,ontology,genes
Classifier: License :: OSI Approved :: MIT License
Classifier: Programming Language :: Python
Classifier: Programming Language :: Python :: 3
Requires-Python: >=3.10
License-File: LICENSE
Requires-Dist: networkx >=3.0
Requires-Dist: numpy <2.0,>=1.18.5
Requires-Dist: openpyxl
Requires-Dist: pandas
Requires-Dist: requests
Requires-Dist: tqdm
Requires-Dist: xmltodict >=0.13.0
